pyinclusion/__init__.py
pyinclusion/core.py
pyinclusion-0.0.4.dist-info/LICENSE.txt
pyinclusion-0.0.4.dist-info/METADATA
pyinclusion-0.0.4.dist-info/WHEEL
pyinclusion-0.0.4.dist-info/top_level.txt
pyinclusion-0.0.4.dist-info/RECORD
