Metadata-Version: 2.1
Name: pyinclusion
Version: 0.0.4
Summary: A simple library to generate subject inclusion flow chart for epidemiology analysis
Home-page: https://github.com/activityMonitoring/py_inclusion
Author: Hang Yuan
Author-email: angerhangy@gmail.com
License: UNKNOWN
Project-URL: Bug Reports, https://github.com/activityMonitoring/py_inclusion/issues
Project-URL: Source, https://github.com/activityMonitoring/py_inclusion
Keywords: sample,setuptools,development
Platform: UNKNOWN
Classifier: Development Status :: 3 - Alpha
Classifier: Intended Audience :: Science/Research
Classifier: Topic :: Scientific/Engineering :: Visualization
Classifier: License :: OSI Approved :: MIT License
Classifier: Programming Language :: Python :: 3
Classifier: Programming Language :: Python :: 3.6
Classifier: Programming Language :: Python :: 3.7
Classifier: Programming Language :: Python :: 3.8
Classifier: Programming Language :: Python :: 3.9
Classifier: Programming Language :: Python :: 3.10
Classifier: Programming Language :: Python :: 3 :: Only
Requires-Python: >=3.6, <4
License-File: LICENSE.txt
Requires-Dist: pandas
Requires-Dist: numpy
Requires-Dist: pyflowchart
Provides-Extra: dev
Requires-Dist: check-manifest ; extra == 'dev'
Provides-Extra: test
Requires-Dist: coverage ; extra == 'test'
